SolExDataCube/__init__.py
SolExDataCube/main.py
SolExDataCube-0.0.2.dist-info/METADATA
SolExDataCube-0.0.2.dist-info/WHEEL
SolExDataCube-0.0.2.dist-info/top_level.txt
SolExDataCube-0.0.2.dist-info/RECORD
