Metadata-Version: 2.1
Name: SolExDataCube
Version: 0.0.2
